{
 "version": "3.16.7",
 "flags": {},
 "shapes": [
  {
   "label": "box",
   "line_color": [
    0,
    255,
    0,
    255
   ],
   "fill_color": null,
   "points": [
    [
     126,
     175
    ],
    [
     203,
     287
    ]
   ],
   "shape_type": "rectangle",
   "flags": {}
  },
  {
   "label": "point",
   "line_color": null,
   "fill_color": null,
   "points": [
    [
     123,
     219
    ]
   ],
   "shape_type": "point",
   "flags": {}
  },
  {
   "label": "point",
   "line_color": null,
   "fill_color": null,
   "points": [
    [
     125,
     224
    ]
   ],
   "shape_type": "point",
   "flags": {}
  },
  {
   "label": "point",
   "line_color": null,
   "fill_color": null,
   "points": [
    [
     127,
     229
    ]
   ],
   "shape_type": "point",
   "flags": {}
  },
  {
   "label": "point",
   "line_color": null,
   "fill_color": null,
   "points": [
    [
     129,
     234
    ]
   ],
   "shape_type": "point",
   "flags": {}
  },
  {
   "label": "point",
   "line_color": null,
   "fill_color": null,
   "points": [
    [
     130,
     239
    ]
   ],
   "shape_type": "point",
   "flags": {}
  },
  {
   "label": "point",
   "line_color": null,
   "fill_color": null,
   "points": [
    [
     132,
     245
    ]
   ],
   "shape_type": "point",
   "flags": {}
  },
  {
   "label": "point",
   "line_color": null,
   "fill_color": null,
   "points": [
    [
     134,
     250
    ]
   ],
   "shape_type": "point",
   "flags": {}
  },
  {
   "label": "point",
   "line_color": null,
   "fill_color": null,
   "points": [
    [
     137,
     254
    ]
   ],
   "shape_type": "point",
   "flags": {}
  },
  {
   "label": "point",
   "line_color": null,
   "fill_color": null,
   "points": [
    [
     141,
     259
    ]
   ],
   "shape_type": "point",
   "flags": {}
  },
  {
   "label": "point",
   "line_color": null,
   "fill_color": null,
   "points": [
    [
     144,
     263
    ]
   ],
   "shape_type": "point",
   "flags": {}
  },
  {
   "label": "point",
   "line_color": null,
   "fill_color": null,
   "points": [
    [
     149,
     266
    ]
   ],
   "shape_type": "point",
   "flags": {}
  },
  {
   "label": "point",
   "line_color": null,
   "fill_color": null,
   "points": [
    [
     153,
     269
    ]
   ],
   "shape_type": "point",
   "flags": {}
  },
  {
   "label": "point",
   "line_color": null,
   "fill_color": null,
   "points": [
    [
     158,
     271
    ]
   ],
   "shape_type": "point",
   "flags": {}
  },
  {
   "label": "point",
   "line_color": null,
   "fill_color": null,
   "points": [
    [
     164,
     273
    ]
   ],
   "shape_type": "point",
   "flags": {}
  },
  {
   "label": "point",
   "line_color": null,
   "fill_color": null,
   "points": [
    [
     169,
     273
    ]
   ],
   "shape_type": "point",
   "flags": {}
  },
  {
   "label": "point",
   "line_color": null,
   "fill_color": null,
   "points": [
    [
     175,
     274
    ]
   ],
   "shape_type": "point",
   "flags": {}
  },
  {
   "label": "point",
   "line_color": null,
   "fill_color": null,
   "points": [
    [
     180,
     274
    ]
   ],
   "shape_type": "point",
   "flags": {}
  },
  {
   "label": "point",
   "line_color": null,
   "fill_color": null,
   "points": [
    [
     184,
     274
    ]
   ],
   "shape_type": "point",
   "flags": {}
  },
  {
   "label": "point",
   "line_color": null,
   "fill_color": null,
   "points": [
    [
     188,
     271
    ]
   ],
   "shape_type": "point",
   "flags": {}
  },
  {
   "label": "point",
   "line_color": null,
   "fill_color": null,
   "points": [
    [
     191,
     268
    ]
   ],
   "shape_type": "point",
   "flags": {}
  },
  {
   "label": "point",
   "line_color": null,
   "fill_color": null,
   "points": [
    [
     193,
     264
    ]
   ],
   "shape_type": "point",
   "flags": {}
  },
  {
   "label": "point",
   "line_color": null,
   "fill_color": null,
   "points": [
    [
     194,
     260
    ]
   ],
   "shape_type": "point",
   "flags": {}
  },
  {
   "label": "point",
   "line_color": null,
   "fill_color": null,
   "points": [
    [
     196,
     256
    ]
   ],
   "shape_type": "point",
   "flags": {}
  },
  {
   "label": "point",
   "line_color": null,
   "fill_color": null,
   "points": [
    [
     197,
     251
    ]
   ],
   "shape_type": "point",
   "flags": {}
  },
  {
   "label": "point",
   "line_color": null,
   "fill_color": null,
   "points": [
    [
     198,
     247
    ]
   ],
   "shape_type": "point",
   "flags": {}
  },
  {
   "label": "point",
   "line_color": null,
   "fill_color": null,
   "points": [
    [
     198,
     243
    ]
   ],
   "shape_type": "point",
   "flags": {}
  },
  {
   "label": "point",
   "line_color": null,
   "fill_color": null,
   "points": [
    [
     198,
     238
    ]
   ],
   "shape_type": "point",
   "flags": {}
  },
  {
   "label": "point",
   "line_color": null,
   "fill_color": null,
   "points": [
    [
     198,
     234
    ]
   ],
   "shape_type": "point",
   "flags": {}
  },
  {
   "label": "point",
   "line_color": null,
   "fill_color": null,
   "points": [
    [
     197,
     229
    ]
   ],
   "shape_type": "point",
   "flags": {}
  },
  {
   "label": "point",
   "line_color": null,
   "fill_color": null,
   "points": [
    [
     197,
     225
    ]
   ],
   "shape_type": "point",
   "flags": {}
  },
  {
   "label": "point",
   "line_color": null,
   "fill_color": null,
   "points": [
    [
     196,
     221
    ]
   ],
   "shape_type": "point",
   "flags": {}
  },
  {
   "label": "point",
   "line_color": null,
   "fill_color": null,
   "points": [
    [
     195,
     217
    ]
   ],
   "shape_type": "point",
   "flags": {}
  },
  {
   "label": "point",
   "line_color": null,
   "fill_color": null,
   "points": [
    [
     195,
     212
    ]
   ],
   "shape_type": "point",
   "flags": {}
  },
  {
   "label": "point",
   "line_color": null,
   "fill_color": null,
   "points": [
    [
     137,
     214
    ]
   ],
   "shape_type": "point",
   "flags": {}
  },
  {
   "label": "point",
   "line_color": null,
   "fill_color": null,
   "points": [
    [
     144,
     206
    ]
   ],
   "shape_type": "point",
   "flags": {}
  },
  {
   "label": "point",
   "line_color": null,
   "fill_color": null,
   "points": [
    [
     152,
     204
    ]
   ],
   "shape_type": "point",
   "flags": {}
  },
  {
   "label": "point",
   "line_color": null,
   "fill_color": null,
   "points": [
    [
     159,
     203
    ]
   ],
   "shape_type": "point",
   "flags": {}
  },
  {
   "label": "point",
   "line_color": null,
   "fill_color": null,
   "points": [
    [
     166,
     206
    ]
   ],
   "shape_type": "point",
   "flags": {}
  },
  {
   "label": "point",
   "line_color": null,
   "fill_color": null,
   "points": [
    [
     166,
     210
    ]
   ],
   "shape_type": "point",
   "flags": {}
  },
  {
   "label": "point",
   "line_color": null,
   "fill_color": null,
   "points": [
    [
     160,
     208
    ]
   ],
   "shape_type": "point",
   "flags": {}
  },
  {
   "label": "point",
   "line_color": null,
   "fill_color": null,
   "points": [
    [
     152,
     208
    ]
   ],
   "shape_type": "point",
   "flags": {}
  },
  {
   "label": "point",
   "line_color": null,
   "fill_color": null,
   "points": [
    [
     145,
     210
    ]
   ],
   "shape_type": "point",
   "flags": {}
  },
  {
   "label": "point",
   "line_color": null,
   "fill_color": null,
   "points": [
    [
     178,
     207
    ]
   ],
   "shape_type": "point",
   "flags": {}
  },
  {
   "label": "point",
   "line_color": null,
   "fill_color": null,
   "points": [
    [
     181,
     203
    ]
   ],
   "shape_type": "point",
   "flags": {}
  },
  {
   "label": "point",
   "line_color": null,
   "fill_color": null,
   "points": [
    [
     185,
     201
    ]
   ],
   "shape_type": "point",
   "flags": {}
  },
  {
   "label": "point",
   "line_color": null,
   "fill_color": null,
   "points": [
    [
     189,
     201
    ]
   ],
   "shape_type": "point",
   "flags": {}
  },
  {
   "label": "point",
   "line_color": null,
   "fill_color": null,
   "points": [
    [
     194,
     208
    ]
   ],
   "shape_type": "point",
   "flags": {}
  },
  {
   "label": "point",
   "line_color": null,
   "fill_color": null,
   "points": [
    [
     190,
     206
    ]
   ],
   "shape_type": "point",
   "flags": {}
  },
  {
   "label": "point",
   "line_color": null,
   "fill_color": null,
   "points": [
    [
     185,
     207
    ]
   ],
   "shape_type": "point",
   "flags": {}
  },
  {
   "label": "point",
   "line_color": null,
   "fill_color": null,
   "points": [
    [
     182,
     209
    ]
   ],
   "shape_type": "point",
   "flags": {}
  },
  {
   "label": "point",
   "line_color": null,
   "fill_color": null,
   "points": [
    [
     178,
     211
    ]
   ],
   "shape_type": "point",
   "flags": {}
  },
  {
   "label": "point",
   "line_color": null,
   "fill_color": null,
   "points": [
    [
     175,
     217
    ]
   ],
   "shape_type": "point",
   "flags": {}
  },
  {
   "label": "point",
   "line_color": null,
   "fill_color": null,
   "points": [
    [
     176,
     223
    ]
   ],
   "shape_type": "point",
   "flags": {}
  },
  {
   "label": "point",
   "line_color": null,
   "fill_color": null,
   "points": [
    [
     177,
     229
    ]
   ],
   "shape_type": "point",
   "flags": {}
  },
  {
   "label": "point",
   "line_color": null,
   "fill_color": null,
   "points": [
    [
     179,
     235
    ]
   ],
   "shape_type": "point",
   "flags": {}
  },
  {
   "label": "point",
   "line_color": null,
   "fill_color": null,
   "points": [
    [
     167,
     240
    ]
   ],
   "shape_type": "point",
   "flags": {}
  },
  {
   "label": "point",
   "line_color": null,
   "fill_color": null,
   "points": [
    [
     173,
     241
    ]
   ],
   "shape_type": "point",
   "flags": {}
  },
  {
   "label": "point",
   "line_color": null,
   "fill_color": null,
   "points": [
    [
     178,
     241
    ]
   ],
   "shape_type": "point",
   "flags": {}
  },
  {
   "label": "point",
   "line_color": null,
   "fill_color": null,
   "points": [
    [
     180,
     240
    ]
   ],
   "shape_type": "point",
   "flags": {}
  },
  {
   "label": "point",
   "line_color": null,
   "fill_color": null,
   "points": [
    [
     182,
     239
    ]
   ],
   "shape_type": "point",
   "flags": {}
  },
  {
   "label": "point",
   "line_color": null,
   "fill_color": null,
   "points": [
    [
     150,
     218
    ]
   ],
   "shape_type": "point",
   "flags": {}
  },
  {
   "label": "point",
   "line_color": null,
   "fill_color": null,
   "points": [
    [
     153,
     216
    ]
   ],
   "shape_type": "point",
   "flags": {}
  },
  {
   "label": "point",
   "line_color": null,
   "fill_color": null,
   "points": [
    [
     156,
     215
    ]
   ],
   "shape_type": "point",
   "flags": {}
  },
  {
   "label": "point",
   "line_color": null,
   "fill_color": null,
   "points": [
    [
     159,
     216
    ]
   ],
   "shape_type": "point",
   "flags": {}
  },
  {
   "label": "point",
   "line_color": null,
   "fill_color": null,
   "points": [
    [
     161,
     218
    ]
   ],
   "shape_type": "point",
   "flags": {}
  },
  {
   "label": "point",
   "line_color": null,
   "fill_color": null,
   "points": [
    [
     159,
     219
    ]
   ],
   "shape_type": "point",
   "flags": {}
  },
  {
   "label": "point",
   "line_color": null,
   "fill_color": null,
   "points": [
    [
     157,
     219
    ]
   ],
   "shape_type": "point",
   "flags": {}
  },
  {
   "label": "point",
   "line_color": null,
   "fill_color": null,
   "points": [
    [
     153,
     219
    ]
   ],
   "shape_type": "point",
   "flags": {}
  },
  {
   "label": "point",
   "line_color": null,
   "fill_color": null,
   "points": [
    [
     182,
     215
    ]
   ],
   "shape_type": "point",
   "flags": {}
  },
  {
   "label": "point",
   "line_color": null,
   "fill_color": null,
   "points": [
    [
     185,
     213
    ]
   ],
   "shape_type": "point",
   "flags": {}
  },
  {
   "label": "point",
   "line_color": null,
   "fill_color": null,
   "points": [
    [
     189,
     213
    ]
   ],
   "shape_type": "point",
   "flags": {}
  },
  {
   "label": "point",
   "line_color": null,
   "fill_color": null,
   "points": [
    [
     190,
     214
    ]
   ],
   "shape_type": "point",
   "flags": {}
  },
  {
   "label": "point",
   "line_color": null,
   "fill_color": null,
   "points": [
    [
     191,
     214
    ]
   ],
   "shape_type": "point",
   "flags": {}
  },
  {
   "label": "point",
   "line_color": null,
   "fill_color": null,
   "points": [
    [
     190,
     215
    ]
   ],
   "shape_type": "point",
   "flags": {}
  },
  {
   "label": "point",
   "line_color": null,
   "fill_color": null,
   "points": [
    [
     189,
     216
    ]
   ],
   "shape_type": "point",
   "flags": {}
  },
  {
   "label": "point",
   "line_color": null,
   "fill_color": null,
   "points": [
    [
     185,
     216
    ]
   ],
   "shape_type": "point",
   "flags": {}
  },
  {
   "label": "point",
   "line_color": null,
   "fill_color": null,
   "points": [
    [
     158,
     250
    ]
   ],
   "shape_type": "point",
   "flags": {}
  },
  {
   "label": "point",
   "line_color": null,
   "fill_color": null,
   "points": [
    [
     167,
     247
    ]
   ],
   "shape_type": "point",
   "flags": {}
  },
  {
   "label": "point",
   "line_color": null,
   "fill_color": null,
   "points": [
    [
     176,
     247
    ]
   ],
   "shape_type": "point",
   "flags": {}
  },
  {
   "label": "point",
   "line_color": null,
   "fill_color": null,
   "points": [
    [
     178,
     247
    ]
   ],
   "shape_type": "point",
   "flags": {}
  },
  {
   "label": "point",
   "line_color": null,
   "fill_color": null,
   "points": [
    [
     180,
     246
    ]
   ],
   "shape_type": "point",
   "flags": {}
  },
  {
   "label": "point",
   "line_color": null,
   "fill_color": null,
   "points": [
    [
     183,
     246
    ]
   ],
   "shape_type": "point",
   "flags": {}
  },
  {
   "label": "point",
   "line_color": null,
   "fill_color": null,
   "points": [
    [
     186,
     246
    ]
   ],
   "shape_type": "point",
   "flags": {}
  },
  {
   "label": "point",
   "line_color": null,
   "fill_color": null,
   "points": [
    [
     185,
     251
    ]
   ],
   "shape_type": "point",
   "flags": {}
  },
  {
   "label": "point",
   "line_color": null,
   "fill_color": null,
   "points": [
    [
     182,
     255
    ]
   ],
   "shape_type": "point",
   "flags": {}
  },
  {
   "label": "point",
   "line_color": null,
   "fill_color": null,
   "points": [
    [
     178,
     258
    ]
   ],
   "shape_type": "point",
   "flags": {}
  },
  {
   "label": "point",
   "line_color": null,
   "fill_color": null,
   "points": [
    [
     170,
     258
    ]
   ],
   "shape_type": "point",
   "flags": {}
  },
  {
   "label": "point",
   "line_color": null,
   "fill_color": null,
   "points": [
    [
     163,
     256
    ]
   ],
   "shape_type": "point",
   "flags": {}
  },
  {
   "label": "point",
   "line_color": null,
   "fill_color": null,
   "points": [
    [
     159,
     250
    ]
   ],
   "shape_type": "point",
   "flags": {}
  },
  {
   "label": "point",
   "line_color": null,
   "fill_color": null,
   "points": [
    [
     168,
     250
    ]
   ],
   "shape_type": "point",
   "flags": {}
  },
  {
   "label": "point",
   "line_color": null,
   "fill_color": null,
   "points": [
    [
     177,
     248
    ]
   ],
   "shape_type": "point",
   "flags": {}
  },
  {
   "label": "point",
   "line_color": null,
   "fill_color": null,
   "points": [
    [
     182,
     247
    ]
   ],
   "shape_type": "point",
   "flags": {}
  },
  {
   "label": "point",
   "line_color": null,
   "fill_color": null,
   "points": [
    [
     186,
     247
    ]
   ],
   "shape_type": "point",
   "flags": {}
  },
  {
   "label": "point",
   "line_color": null,
   "fill_color": null,
   "points": [
    [
     182,
     252
    ]
   ],
   "shape_type": "point",
   "flags": {}
  },
  {
   "label": "point",
   "line_color": null,
   "fill_color": null,
   "points": [
    [
     177,
     255
    ]
   ],
   "shape_type": "point",
   "flags": {}
  },
  {
   "label": "point",
   "line_color": null,
   "fill_color": null,
   "points": [
    [
     168,
     254
    ]
   ],
   "shape_type": "point",
   "flags": {}
  },
  {
   "label": "point",
   "line_color": null,
   "fill_color": null,
   "points": [
    [
     154,
     217
    ]
   ],
   "shape_type": "point",
   "flags": {}
  },
  {
   "label": "point",
   "line_color": null,
   "fill_color": null,
   "points": [
    [
     186,
     214
    ]
   ],
   "shape_type": "point",
   "flags": {}
  }
 ],
 "lineColor": [
  0,
  255,
  0,
  128
 ],
 "fillColor": [
  255,
  0,
  0,
  128
 ],
 "imagePath": "40_Gymnastics_Gymnastics_40_931.jpg",
 "imageData": null,
 "imageHeight": 1195,
 "imageWidth": 1024
}