{
 "version": "3.16.7",
 "flags": {},
 "shapes": [
  {
   "label": "box",
   "line_color": [
    0,
    255,
    0,
    255
   ],
   "fill_color": null,
   "points": [
    [
     412,
     102
    ],
    [
     542,
     252
    ]
   ],
   "shape_type": "rectangle",
   "flags": {}
  },
  {
   "label": "point",
   "line_color": null,
   "fill_color": null,
   "points": [
    [
     411,
     154
    ]
   ],
   "shape_type": "point",
   "flags": {}
  },
  {
   "label": "point",
   "line_color": null,
   "fill_color": null,
   "points": [
    [
     412,
     163
    ]
   ],
   "shape_type": "point",
   "flags": {}
  },
  {
   "label": "point",
   "line_color": null,
   "fill_color": null,
   "points": [
    [
     414,
     171
    ]
   ],
   "shape_type": "point",
   "flags": {}
  },
  {
   "label": "point",
   "line_color": null,
   "fill_color": null,
   "points": [
    [
     415,
     180
    ]
   ],
   "shape_type": "point",
   "flags": {}
  },
  {
   "label": "point",
   "line_color": null,
   "fill_color": null,
   "points": [
    [
     418,
     189
    ]
   ],
   "shape_type": "point",
   "flags": {}
  },
  {
   "label": "point",
   "line_color": null,
   "fill_color": null,
   "points": [
    [
     420,
     198
    ]
   ],
   "shape_type": "point",
   "flags": {}
  },
  {
   "label": "point",
   "line_color": null,
   "fill_color": null,
   "points": [
    [
     424,
     206
    ]
   ],
   "shape_type": "point",
   "flags": {}
  },
  {
   "label": "point",
   "line_color": null,
   "fill_color": null,
   "points": [
    [
     429,
     213
    ]
   ],
   "shape_type": "point",
   "flags": {}
  },
  {
   "label": "point",
   "line_color": null,
   "fill_color": null,
   "points": [
    [
     436,
     219
    ]
   ],
   "shape_type": "point",
   "flags": {}
  },
  {
   "label": "point",
   "line_color": null,
   "fill_color": null,
   "points": [
    [
     443,
     225
    ]
   ],
   "shape_type": "point",
   "flags": {}
  },
  {
   "label": "point",
   "line_color": null,
   "fill_color": null,
   "points": [
    [
     450,
     230
    ]
   ],
   "shape_type": "point",
   "flags": {}
  },
  {
   "label": "point",
   "line_color": null,
   "fill_color": null,
   "points": [
    [
     457,
     235
    ]
   ],
   "shape_type": "point",
   "flags": {}
  },
  {
   "label": "point",
   "line_color": null,
   "fill_color": null,
   "points": [
    [
     465,
     241
    ]
   ],
   "shape_type": "point",
   "flags": {}
  },
  {
   "label": "point",
   "line_color": null,
   "fill_color": null,
   "points": [
    [
     472,
     245
    ]
   ],
   "shape_type": "point",
   "flags": {}
  },
  {
   "label": "point",
   "line_color": null,
   "fill_color": null,
   "points": [
    [
     480,
     249
    ]
   ],
   "shape_type": "point",
   "flags": {}
  },
  {
   "label": "point",
   "line_color": null,
   "fill_color": null,
   "points": [
    [
     489,
     250
    ]
   ],
   "shape_type": "point",
   "flags": {}
  },
  {
   "label": "point",
   "line_color": null,
   "fill_color": null,
   "points": [
    [
     498,
     250
    ]
   ],
   "shape_type": "point",
   "flags": {}
  },
  {
   "label": "point",
   "line_color": null,
   "fill_color": null,
   "points": [
    [
     506,
     248
    ]
   ],
   "shape_type": "point",
   "flags": {}
  },
  {
   "label": "point",
   "line_color": null,
   "fill_color": null,
   "points": [
    [
     514,
     245
    ]
   ],
   "shape_type": "point",
   "flags": {}
  },
  {
   "label": "point",
   "line_color": null,
   "fill_color": null,
   "points": [
    [
     521,
     241
    ]
   ],
   "shape_type": "point",
   "flags": {}
  },
  {
   "label": "point",
   "line_color": null,
   "fill_color": null,
   "points": [
    [
     526,
     234
    ]
   ],
   "shape_type": "point",
   "flags": {}
  },
  {
   "label": "point",
   "line_color": null,
   "fill_color": null,
   "points": [
    [
     530,
     227
    ]
   ],
   "shape_type": "point",
   "flags": {}
  },
  {
   "label": "point",
   "line_color": null,
   "fill_color": null,
   "points": [
    [
     533,
     219
    ]
   ],
   "shape_type": "point",
   "flags": {}
  },
  {
   "label": "point",
   "line_color": null,
   "fill_color": null,
   "points": [
    [
     537,
     212
    ]
   ],
   "shape_type": "point",
   "flags": {}
  },
  {
   "label": "point",
   "line_color": null,
   "fill_color": null,
   "points": [
    [
     540,
     204
    ]
   ],
   "shape_type": "point",
   "flags": {}
  },
  {
   "label": "point",
   "line_color": null,
   "fill_color": null,
   "points": [
    [
     541,
     196
    ]
   ],
   "shape_type": "point",
   "flags": {}
  },
  {
   "label": "point",
   "line_color": null,
   "fill_color": null,
   "points": [
    [
     541,
     188
    ]
   ],
   "shape_type": "point",
   "flags": {}
  },
  {
   "label": "point",
   "line_color": null,
   "fill_color": null,
   "points": [
    [
     540,
     179
    ]
   ],
   "shape_type": "point",
   "flags": {}
  },
  {
   "label": "point",
   "line_color": null,
   "fill_color": null,
   "points": [
    [
     538,
     171
    ]
   ],
   "shape_type": "point",
   "flags": {}
  },
  {
   "label": "point",
   "line_color": null,
   "fill_color": null,
   "points": [
    [
     537,
     163
    ]
   ],
   "shape_type": "point",
   "flags": {}
  },
  {
   "label": "point",
   "line_color": null,
   "fill_color": null,
   "points": [
    [
     535,
     155
    ]
   ],
   "shape_type": "point",
   "flags": {}
  },
  {
   "label": "point",
   "line_color": null,
   "fill_color": null,
   "points": [
    [
     535,
     147
    ]
   ],
   "shape_type": "point",
   "flags": {}
  },
  {
   "label": "point",
   "line_color": null,
   "fill_color": null,
   "points": [
    [
     535,
     139
    ]
   ],
   "shape_type": "point",
   "flags": {}
  },
  {
   "label": "point",
   "line_color": null,
   "fill_color": null,
   "points": [
    [
     434,
     167
    ]
   ],
   "shape_type": "point",
   "flags": {}
  },
  {
   "label": "point",
   "line_color": null,
   "fill_color": null,
   "points": [
    [
     444,
     156
    ]
   ],
   "shape_type": "point",
   "flags": {}
  },
  {
   "label": "point",
   "line_color": null,
   "fill_color": null,
   "points": [
    [
     454,
     154
    ]
   ],
   "shape_type": "point",
   "flags": {}
  },
  {
   "label": "point",
   "line_color": null,
   "fill_color": null,
   "points": [
    [
     464,
     153
    ]
   ],
   "shape_type": "point",
   "flags": {}
  },
  {
   "label": "point",
   "line_color": null,
   "fill_color": null,
   "points": [
    [
     473,
     154
    ]
   ],
   "shape_type": "point",
   "flags": {}
  },
  {
   "label": "point",
   "line_color": null,
   "fill_color": null,
   "points": [
    [
     473,
     158
    ]
   ],
   "shape_type": "point",
   "flags": {}
  },
  {
   "label": "point",
   "line_color": null,
   "fill_color": null,
   "points": [
    [
     465,
     158
    ]
   ],
   "shape_type": "point",
   "flags": {}
  },
  {
   "label": "point",
   "line_color": null,
   "fill_color": null,
   "points": [
    [
     455,
     159
    ]
   ],
   "shape_type": "point",
   "flags": {}
  },
  {
   "label": "point",
   "line_color": null,
   "fill_color": null,
   "points": [
    [
     445,
     162
    ]
   ],
   "shape_type": "point",
   "flags": {}
  },
  {
   "label": "point",
   "line_color": null,
   "fill_color": null,
   "points": [
    [
     492,
     151
    ]
   ],
   "shape_type": "point",
   "flags": {}
  },
  {
   "label": "point",
   "line_color": null,
   "fill_color": null,
   "points": [
    [
     501,
     147
    ]
   ],
   "shape_type": "point",
   "flags": {}
  },
  {
   "label": "point",
   "line_color": null,
   "fill_color": null,
   "points": [
    [
     510,
     145
    ]
   ],
   "shape_type": "point",
   "flags": {}
  },
  {
   "label": "point",
   "line_color": null,
   "fill_color": null,
   "points": [
    [
     521,
     145
    ]
   ],
   "shape_type": "point",
   "flags": {}
  },
  {
   "label": "point",
   "line_color": null,
   "fill_color": null,
   "points": [
    [
     530,
     150
    ]
   ],
   "shape_type": "point",
   "flags": {}
  },
  {
   "label": "point",
   "line_color": null,
   "fill_color": null,
   "points": [
    [
     521,
     151
    ]
   ],
   "shape_type": "point",
   "flags": {}
  },
  {
   "label": "point",
   "line_color": null,
   "fill_color": null,
   "points": [
    [
     511,
     151
    ]
   ],
   "shape_type": "point",
   "flags": {}
  },
  {
   "label": "point",
   "line_color": null,
   "fill_color": null,
   "points": [
    [
     502,
     153
    ]
   ],
   "shape_type": "point",
   "flags": {}
  },
  {
   "label": "point",
   "line_color": null,
   "fill_color": null,
   "points": [
    [
     493,
     156
    ]
   ],
   "shape_type": "point",
   "flags": {}
  },
  {
   "label": "point",
   "line_color": null,
   "fill_color": null,
   "points": [
    [
     486,
     164
    ]
   ],
   "shape_type": "point",
   "flags": {}
  },
  {
   "label": "point",
   "line_color": null,
   "fill_color": null,
   "points": [
    [
     489,
     178
    ]
   ],
   "shape_type": "point",
   "flags": {}
  },
  {
   "label": "point",
   "line_color": null,
   "fill_color": null,
   "points": [
    [
     492,
     191
    ]
   ],
   "shape_type": "point",
   "flags": {}
  },
  {
   "label": "point",
   "line_color": null,
   "fill_color": null,
   "points": [
    [
     494,
     205
    ]
   ],
   "shape_type": "point",
   "flags": {}
  },
  {
   "label": "point",
   "line_color": null,
   "fill_color": null,
   "points": [
    [
     475,
     199
    ]
   ],
   "shape_type": "point",
   "flags": {}
  },
  {
   "label": "point",
   "line_color": null,
   "fill_color": null,
   "points": [
    [
     484,
     203
    ]
   ],
   "shape_type": "point",
   "flags": {}
  },
  {
   "label": "point",
   "line_color": null,
   "fill_color": null,
   "points": [
    [
     494,
     205
    ]
   ],
   "shape_type": "point",
   "flags": {}
  },
  {
   "label": "point",
   "line_color": null,
   "fill_color": null,
   "points": [
    [
     501,
     200
    ]
   ],
   "shape_type": "point",
   "flags": {}
  },
  {
   "label": "point",
   "line_color": null,
   "fill_color": null,
   "points": [
    [
     506,
     192
    ]
   ],
   "shape_type": "point",
   "flags": {}
  },
  {
   "label": "point",
   "line_color": null,
   "fill_color": null,
   "points": [
    [
     447,
     170
    ]
   ],
   "shape_type": "point",
   "flags": {}
  },
  {
   "label": "point",
   "line_color": null,
   "fill_color": null,
   "points": [
    [
     452,
     165
    ]
   ],
   "shape_type": "point",
   "flags": {}
  },
  {
   "label": "point",
   "line_color": null,
   "fill_color": null,
   "points": [
    [
     459,
     162
    ]
   ],
   "shape_type": "point",
   "flags": {}
  },
  {
   "label": "point",
   "line_color": null,
   "fill_color": null,
   "points": [
    [
     468,
     163
    ]
   ],
   "shape_type": "point",
   "flags": {}
  },
  {
   "label": "point",
   "line_color": null,
   "fill_color": null,
   "points": [
    [
     476,
     170
    ]
   ],
   "shape_type": "point",
   "flags": {}
  },
  {
   "label": "point",
   "line_color": null,
   "fill_color": null,
   "points": [
    [
     468,
     171
    ]
   ],
   "shape_type": "point",
   "flags": {}
  },
  {
   "label": "point",
   "line_color": null,
   "fill_color": null,
   "points": [
    [
     460,
     173
    ]
   ],
   "shape_type": "point",
   "flags": {}
  },
  {
   "label": "point",
   "line_color": null,
   "fill_color": null,
   "points": [
    [
     454,
     173
    ]
   ],
   "shape_type": "point",
   "flags": {}
  },
  {
   "label": "point",
   "line_color": null,
   "fill_color": null,
   "points": [
    [
     497,
     164
    ]
   ],
   "shape_type": "point",
   "flags": {}
  },
  {
   "label": "point",
   "line_color": null,
   "fill_color": null,
   "points": [
    [
     505,
     158
    ]
   ],
   "shape_type": "point",
   "flags": {}
  },
  {
   "label": "point",
   "line_color": null,
   "fill_color": null,
   "points": [
    [
     514,
     155
    ]
   ],
   "shape_type": "point",
   "flags": {}
  },
  {
   "label": "point",
   "line_color": null,
   "fill_color": null,
   "points": [
    [
     519,
     155
    ]
   ],
   "shape_type": "point",
   "flags": {}
  },
  {
   "label": "point",
   "line_color": null,
   "fill_color": null,
   "points": [
    [
     524,
     158
    ]
   ],
   "shape_type": "point",
   "flags": {}
  },
  {
   "label": "point",
   "line_color": null,
   "fill_color": null,
   "points": [
    [
     520,
     162
    ]
   ],
   "shape_type": "point",
   "flags": {}
  },
  {
   "label": "point",
   "line_color": null,
   "fill_color": null,
   "points": [
    [
     515,
     164
    ]
   ],
   "shape_type": "point",
   "flags": {}
  },
  {
   "label": "point",
   "line_color": null,
   "fill_color": null,
   "points": [
    [
     506,
     164
    ]
   ],
   "shape_type": "point",
   "flags": {}
  },
  {
   "label": "point",
   "line_color": null,
   "fill_color": null,
   "points": [
    [
     460,
     210
    ]
   ],
   "shape_type": "point",
   "flags": {}
  },
  {
   "label": "point",
   "line_color": null,
   "fill_color": null,
   "points": [
    [
     476,
     208
    ]
   ],
   "shape_type": "point",
   "flags": {}
  },
  {
   "label": "point",
   "line_color": null,
   "fill_color": null,
   "points": [
    [
     491,
     208
    ]
   ],
   "shape_type": "point",
   "flags": {}
  },
  {
   "label": "point",
   "line_color": null,
   "fill_color": null,
   "points": [
    [
     494,
     208
    ]
   ],
   "shape_type": "point",
   "flags": {}
  },
  {
   "label": "point",
   "line_color": null,
   "fill_color": null,
   "points": [
    [
     497,
     207
    ]
   ],
   "shape_type": "point",
   "flags": {}
  },
  {
   "label": "point",
   "line_color": null,
   "fill_color": null,
   "points": [
    [
     508,
     202
    ]
   ],
   "shape_type": "point",
   "flags": {}
  },
  {
   "label": "point",
   "line_color": null,
   "fill_color": null,
   "points": [
    [
     519,
     198
    ]
   ],
   "shape_type": "point",
   "flags": {}
  },
  {
   "label": "point",
   "line_color": null,
   "fill_color": null,
   "points": [
    [
     515,
     211
    ]
   ],
   "shape_type": "point",
   "flags": {}
  },
  {
   "label": "point",
   "line_color": null,
   "fill_color": null,
   "points": [
    [
     507,
     220
    ]
   ],
   "shape_type": "point",
   "flags": {}
  },
  {
   "label": "point",
   "line_color": null,
   "fill_color": null,
   "points": [
    [
     496,
     226
    ]
   ],
   "shape_type": "point",
   "flags": {}
  },
  {
   "label": "point",
   "line_color": null,
   "fill_color": null,
   "points": [
    [
     482,
     226
    ]
   ],
   "shape_type": "point",
   "flags": {}
  },
  {
   "label": "point",
   "line_color": null,
   "fill_color": null,
   "points": [
    [
     470,
     220
    ]
   ],
   "shape_type": "point",
   "flags": {}
  },
  {
   "label": "point",
   "line_color": null,
   "fill_color": null,
   "points": [
    [
     464,
     212
    ]
   ],
   "shape_type": "point",
   "flags": {}
  },
  {
   "label": "point",
   "line_color": null,
   "fill_color": null,
   "points": [
    [
     479,
     212
    ]
   ],
   "shape_type": "point",
   "flags": {}
  },
  {
   "label": "point",
   "line_color": null,
   "fill_color": null,
   "points": [
    [
     494,
     210
    ]
   ],
   "shape_type": "point",
   "flags": {}
  },
  {
   "label": "point",
   "line_color": null,
   "fill_color": null,
   "points": [
    [
     506,
     206
    ]
   ],
   "shape_type": "point",
   "flags": {}
  },
  {
   "label": "point",
   "line_color": null,
   "fill_color": null,
   "points": [
    [
     516,
     201
    ]
   ],
   "shape_type": "point",
   "flags": {}
  },
  {
   "label": "point",
   "line_color": null,
   "fill_color": null,
   "points": [
    [
     508,
     214
    ]
   ],
   "shape_type": "point",
   "flags": {}
  },
  {
   "label": "point",
   "line_color": null,
   "fill_color": null,
   "points": [
    [
     495,
     223
    ]
   ],
   "shape_type": "point",
   "flags": {}
  },
  {
   "label": "point",
   "line_color": null,
   "fill_color": null,
   "points": [
    [
     478,
     222
    ]
   ],
   "shape_type": "point",
   "flags": {}
  },
  {
   "label": "point",
   "line_color": null,
   "fill_color": null,
   "points": [
    [
     462,
     168
    ]
   ],
   "shape_type": "point",
   "flags": {}
  },
  {
   "label": "point",
   "line_color": null,
   "fill_color": null,
   "points": [
    [
     518,
     158
    ]
   ],
   "shape_type": "point",
   "flags": {}
  }
 ],
 "lineColor": [
  0,
  255,
  0,
  128
 ],
 "fillColor": [
  255,
  0,
  0,
  128
 ],
 "imagePath": "35_Basketball_basketballgame_ball_35_358.jpg",
 "imageData": null,
 "imageHeight": 684,
 "imageWidth": 1024
}