{
 "version": "3.16.7",
 "flags": {},
 "shapes": [
  {
   "label": "box",
   "line_color": [
    1,
    255,
    0,
    255
   ],
   "fill_color": null,
   "points": [
    [
     599,
     130
    ],
    [
     717,
     329
    ]
   ],
   "shape_type": "rectangle",
   "flags": {}
  },
  {
   "label": "point",
   "line_color": null,
   "fill_color": null,
   "points": [
    [
     600,
     196
    ]
   ],
   "shape_type": "point",
   "flags": {}
  },
  {
   "label": "point",
   "line_color": null,
   "fill_color": null,
   "points": [
    [
     604,
     205
    ]
   ],
   "shape_type": "point",
   "flags": {}
  },
  {
   "label": "point",
   "line_color": null,
   "fill_color": null,
   "points": [
    [
     604,
     214
    ]
   ],
   "shape_type": "point",
   "flags": {}
  },
  {
   "label": "point",
   "line_color": null,
   "fill_color": null,
   "points": [
    [
     603,
     223
    ]
   ],
   "shape_type": "point",
   "flags": {}
  },
  {
   "label": "point",
   "line_color": null,
   "fill_color": null,
   "points": [
    [
     602,
     232
    ]
   ],
   "shape_type": "point",
   "flags": {}
  },
  {
   "label": "point",
   "line_color": null,
   "fill_color": null,
   "points": [
    [
     600,
     241
    ]
   ],
   "shape_type": "point",
   "flags": {}
  },
  {
   "label": "point",
   "line_color": null,
   "fill_color": null,
   "points": [
    [
     602,
     250
    ]
   ],
   "shape_type": "point",
   "flags": {}
  },
  {
   "label": "point",
   "line_color": null,
   "fill_color": null,
   "points": [
    [
     608,
     258
    ]
   ],
   "shape_type": "point",
   "flags": {}
  },
  {
   "label": "point",
   "line_color": null,
   "fill_color": null,
   "points": [
    [
     614,
     265
    ]
   ],
   "shape_type": "point",
   "flags": {}
  },
  {
   "label": "point",
   "line_color": null,
   "fill_color": null,
   "points": [
    [
     619,
     272
    ]
   ],
   "shape_type": "point",
   "flags": {}
  },
  {
   "label": "point",
   "line_color": null,
   "fill_color": null,
   "points": [
    [
     622,
     281
    ]
   ],
   "shape_type": "point",
   "flags": {}
  },
  {
   "label": "point",
   "line_color": null,
   "fill_color": null,
   "points": [
    [
     622,
     290
    ]
   ],
   "shape_type": "point",
   "flags": {}
  },
  {
   "label": "point",
   "line_color": null,
   "fill_color": null,
   "points": [
    [
     625,
     299
    ]
   ],
   "shape_type": "point",
   "flags": {}
  },
  {
   "label": "point",
   "line_color": null,
   "fill_color": null,
   "points": [
    [
     625,
     308
    ]
   ],
   "shape_type": "point",
   "flags": {}
  },
  {
   "label": "point",
   "line_color": null,
   "fill_color": null,
   "points": [
    [
     626,
     317
    ]
   ],
   "shape_type": "point",
   "flags": {}
  },
  {
   "label": "point",
   "line_color": null,
   "fill_color": null,
   "points": [
    [
     631,
     325
    ]
   ],
   "shape_type": "point",
   "flags": {}
  },
  {
   "label": "point",
   "line_color": null,
   "fill_color": null,
   "points": [
    [
     639,
     328
    ]
   ],
   "shape_type": "point",
   "flags": {}
  },
  {
   "label": "point",
   "line_color": null,
   "fill_color": null,
   "points": [
    [
     651,
     328
    ]
   ],
   "shape_type": "point",
   "flags": {}
  },
  {
   "label": "point",
   "line_color": null,
   "fill_color": null,
   "points": [
    [
     663,
     326
    ]
   ],
   "shape_type": "point",
   "flags": {}
  },
  {
   "label": "point",
   "line_color": null,
   "fill_color": null,
   "points": [
    [
     674,
     322
    ]
   ],
   "shape_type": "point",
   "flags": {}
  },
  {
   "label": "point",
   "line_color": null,
   "fill_color": null,
   "points": [
    [
     685,
     318
    ]
   ],
   "shape_type": "point",
   "flags": {}
  },
  {
   "label": "point",
   "line_color": null,
   "fill_color": null,
   "points": [
    [
     695,
     313
    ]
   ],
   "shape_type": "point",
   "flags": {}
  },
  {
   "label": "point",
   "line_color": null,
   "fill_color": null,
   "points": [
    [
     705,
     306
    ]
   ],
   "shape_type": "point",
   "flags": {}
  },
  {
   "label": "point",
   "line_color": null,
   "fill_color": null,
   "points": [
    [
     713,
     298
    ]
   ],
   "shape_type": "point",
   "flags": {}
  },
  {
   "label": "point",
   "line_color": null,
   "fill_color": null,
   "points": [
    [
     721,
     289
    ]
   ],
   "shape_type": "point",
   "flags": {}
  },
  {
   "label": "point",
   "line_color": null,
   "fill_color": null,
   "points": [
    [
     728,
     280
    ]
   ],
   "shape_type": "point",
   "flags": {}
  },
  {
   "label": "point",
   "line_color": null,
   "fill_color": null,
   "points": [
    [
     733,
     269
    ]
   ],
   "shape_type": "point",
   "flags": {}
  },
  {
   "label": "point",
   "line_color": null,
   "fill_color": null,
   "points": [
    [
     736,
     258
    ]
   ],
   "shape_type": "point",
   "flags": {}
  },
  {
   "label": "point",
   "line_color": null,
   "fill_color": null,
   "points": [
    [
     737,
     246
    ]
   ],
   "shape_type": "point",
   "flags": {}
  },
  {
   "label": "point",
   "line_color": null,
   "fill_color": null,
   "points": [
    [
     738,
     235
    ]
   ],
   "shape_type": "point",
   "flags": {}
  },
  {
   "label": "point",
   "line_color": null,
   "fill_color": null,
   "points": [
    [
     738,
     223
    ]
   ],
   "shape_type": "point",
   "flags": {}
  },
  {
   "label": "point",
   "line_color": null,
   "fill_color": null,
   "points": [
    [
     738,
     211
    ]
   ],
   "shape_type": "point",
   "flags": {}
  },
  {
   "label": "point",
   "line_color": null,
   "fill_color": null,
   "points": [
    [
     737,
     199
    ]
   ],
   "shape_type": "point",
   "flags": {}
  },
  {
   "label": "point",
   "line_color": null,
   "fill_color": null,
   "points": [
    [
     600,
     187
    ]
   ],
   "shape_type": "point",
   "flags": {}
  },
  {
   "label": "point",
   "line_color": null,
   "fill_color": null,
   "points": [
    [
     605,
     184
    ]
   ],
   "shape_type": "point",
   "flags": {}
  },
  {
   "label": "point",
   "line_color": null,
   "fill_color": null,
   "points": [
    [
     610,
     187
    ]
   ],
   "shape_type": "point",
   "flags": {}
  },
  {
   "label": "point",
   "line_color": null,
   "fill_color": null,
   "points": [
    [
     615,
     190
    ]
   ],
   "shape_type": "point",
   "flags": {}
  },
  {
   "label": "point",
   "line_color": null,
   "fill_color": null,
   "points": [
    [
     620,
     194
    ]
   ],
   "shape_type": "point",
   "flags": {}
  },
  {
   "label": "point",
   "line_color": null,
   "fill_color": null,
   "points": [
    [
     620,
     199
    ]
   ],
   "shape_type": "point",
   "flags": {}
  },
  {
   "label": "point",
   "line_color": null,
   "fill_color": null,
   "points": [
    [
     615,
     196
    ]
   ],
   "shape_type": "point",
   "flags": {}
  },
  {
   "label": "point",
   "line_color": null,
   "fill_color": null,
   "points": [
    [
     610,
     193
    ]
   ],
   "shape_type": "point",
   "flags": {}
  },
  {
   "label": "point",
   "line_color": null,
   "fill_color": null,
   "points": [
    [
     605,
     190
    ]
   ],
   "shape_type": "point",
   "flags": {}
  },
  {
   "label": "point",
   "line_color": null,
   "fill_color": null,
   "points": [
    [
     634,
     184
    ]
   ],
   "shape_type": "point",
   "flags": {}
  },
  {
   "label": "point",
   "line_color": null,
   "fill_color": null,
   "points": [
    [
     646,
     179
    ]
   ],
   "shape_type": "point",
   "flags": {}
  },
  {
   "label": "point",
   "line_color": null,
   "fill_color": null,
   "points": [
    [
     657,
     175
    ]
   ],
   "shape_type": "point",
   "flags": {}
  },
  {
   "label": "point",
   "line_color": null,
   "fill_color": null,
   "points": [
    [
     669,
     177
    ]
   ],
   "shape_type": "point",
   "flags": {}
  },
  {
   "label": "point",
   "line_color": null,
   "fill_color": null,
   "points": [
    [
     681,
     183
    ]
   ],
   "shape_type": "point",
   "flags": {}
  },
  {
   "label": "point",
   "line_color": null,
   "fill_color": null,
   "points": [
    [
     669,
     183
    ]
   ],
   "shape_type": "point",
   "flags": {}
  },
  {
   "label": "point",
   "line_color": null,
   "fill_color": null,
   "points": [
    [
     657,
     182
    ]
   ],
   "shape_type": "point",
   "flags": {}
  },
  {
   "label": "point",
   "line_color": null,
   "fill_color": null,
   "points": [
    [
     645,
     187
    ]
   ],
   "shape_type": "point",
   "flags": {}
  },
  {
   "label": "point",
   "line_color": null,
   "fill_color": null,
   "points": [
    [
     633,
     192
    ]
   ],
   "shape_type": "point",
   "flags": {}
  },
  {
   "label": "point",
   "line_color": null,
   "fill_color": null,
   "points": [
    [
     624,
     204
    ]
   ],
   "shape_type": "point",
   "flags": {}
  },
  {
   "label": "point",
   "line_color": null,
   "fill_color": null,
   "points": [
    [
     618,
     217
    ]
   ],
   "shape_type": "point",
   "flags": {}
  },
  {
   "label": "point",
   "line_color": null,
   "fill_color": null,
   "points": [
    [
     612,
     230
    ]
   ],
   "shape_type": "point",
   "flags": {}
  },
  {
   "label": "point",
   "line_color": null,
   "fill_color": null,
   "points": [
    [
     609,
     244
    ]
   ],
   "shape_type": "point",
   "flags": {}
  },
  {
   "label": "point",
   "line_color": null,
   "fill_color": null,
   "points": [
    [
     606,
     251
    ]
   ],
   "shape_type": "point",
   "flags": {}
  },
  {
   "label": "point",
   "line_color": null,
   "fill_color": null,
   "points": [
    [
     613,
     257
    ]
   ],
   "shape_type": "point",
   "flags": {}
  },
  {
   "label": "point",
   "line_color": null,
   "fill_color": null,
   "points": [
    [
     621,
     257
    ]
   ],
   "shape_type": "point",
   "flags": {}
  },
  {
   "label": "point",
   "line_color": null,
   "fill_color": null,
   "points": [
    [
     631,
     255
    ]
   ],
   "shape_type": "point",
   "flags": {}
  },
  {
   "label": "point",
   "line_color": null,
   "fill_color": null,
   "points": [
    [
     640,
     251
    ]
   ],
   "shape_type": "point",
   "flags": {}
  },
  {
   "label": "point",
   "line_color": null,
   "fill_color": null,
   "points": [
    [
     604,
     205
    ]
   ],
   "shape_type": "point",
   "flags": {}
  },
  {
   "label": "point",
   "line_color": null,
   "fill_color": null,
   "points": [
    [
     604,
     202
    ]
   ],
   "shape_type": "point",
   "flags": {}
  },
  {
   "label": "point",
   "line_color": null,
   "fill_color": null,
   "points": [
    [
     607,
     200
    ]
   ],
   "shape_type": "point",
   "flags": {}
  },
  {
   "label": "point",
   "line_color": null,
   "fill_color": null,
   "points": [
    [
     614,
     201
    ]
   ],
   "shape_type": "point",
   "flags": {}
  },
  {
   "label": "point",
   "line_color": null,
   "fill_color": null,
   "points": [
    [
     619,
     206
    ]
   ],
   "shape_type": "point",
   "flags": {}
  },
  {
   "label": "point",
   "line_color": null,
   "fill_color": null,
   "points": [
    [
     615,
     207
    ]
   ],
   "shape_type": "point",
   "flags": {}
  },
  {
   "label": "point",
   "line_color": null,
   "fill_color": null,
   "points": [
    [
     612,
     207
    ]
   ],
   "shape_type": "point",
   "flags": {}
  },
  {
   "label": "point",
   "line_color": null,
   "fill_color": null,
   "points": [
    [
     608,
     207
    ]
   ],
   "shape_type": "point",
   "flags": {}
  },
  {
   "label": "point",
   "line_color": null,
   "fill_color": null,
   "points": [
    [
     644,
     201
    ]
   ],
   "shape_type": "point",
   "flags": {}
  },
  {
   "label": "point",
   "line_color": null,
   "fill_color": null,
   "points": [
    [
     643,
     198
    ]
   ],
   "shape_type": "point",
   "flags": {}
  },
  {
   "label": "point",
   "line_color": null,
   "fill_color": null,
   "points": [
    [
     649,
     198
    ]
   ],
   "shape_type": "point",
   "flags": {}
  },
  {
   "label": "point",
   "line_color": null,
   "fill_color": null,
   "points": [
    [
     656,
     199
    ]
   ],
   "shape_type": "point",
   "flags": {}
  },
  {
   "label": "point",
   "line_color": null,
   "fill_color": null,
   "points": [
    [
     662,
     203
    ]
   ],
   "shape_type": "point",
   "flags": {}
  },
  {
   "label": "point",
   "line_color": null,
   "fill_color": null,
   "points": [
    [
     658,
     205
    ]
   ],
   "shape_type": "point",
   "flags": {}
  },
  {
   "label": "point",
   "line_color": null,
   "fill_color": null,
   "points": [
    [
     654,
     206
    ]
   ],
   "shape_type": "point",
   "flags": {}
  },
  {
   "label": "point",
   "line_color": null,
   "fill_color": null,
   "points": [
    [
     647,
     206
    ]
   ],
   "shape_type": "point",
   "flags": {}
  },
  {
   "label": "point",
   "line_color": null,
   "fill_color": null,
   "points": [
    [
     623,
     273
    ]
   ],
   "shape_type": "point",
   "flags": {}
  },
  {
   "label": "point",
   "line_color": null,
   "fill_color": null,
   "points": [
    [
     616,
     268
    ]
   ],
   "shape_type": "point",
   "flags": {}
  },
  {
   "label": "point",
   "line_color": null,
   "fill_color": null,
   "points": [
    [
     622,
     267
    ]
   ],
   "shape_type": "point",
   "flags": {}
  },
  {
   "label": "point",
   "line_color": null,
   "fill_color": null,
   "points": [
    [
     625,
     267
    ]
   ],
   "shape_type": "point",
   "flags": {}
  },
  {
   "label": "point",
   "line_color": null,
   "fill_color": null,
   "points": [
    [
     628,
     267
    ]
   ],
   "shape_type": "point",
   "flags": {}
  },
  {
   "label": "point",
   "line_color": null,
   "fill_color": null,
   "points": [
    [
     648,
     268
    ]
   ],
   "shape_type": "point",
   "flags": {}
  },
  {
   "label": "point",
   "line_color": null,
   "fill_color": null,
   "points": [
    [
     668,
     268
    ]
   ],
   "shape_type": "point",
   "flags": {}
  },
  {
   "label": "point",
   "line_color": null,
   "fill_color": null,
   "points": [
    [
     657,
     281
    ]
   ],
   "shape_type": "point",
   "flags": {}
  },
  {
   "label": "point",
   "line_color": null,
   "fill_color": null,
   "points": [
    [
     644,
     291
    ]
   ],
   "shape_type": "point",
   "flags": {}
  },
  {
   "label": "point",
   "line_color": null,
   "fill_color": null,
   "points": [
    [
     628,
     294
    ]
   ],
   "shape_type": "point",
   "flags": {}
  },
  {
   "label": "point",
   "line_color": null,
   "fill_color": null,
   "points": [
    [
     623,
     288
    ]
   ],
   "shape_type": "point",
   "flags": {}
  },
  {
   "label": "point",
   "line_color": null,
   "fill_color": null,
   "points": [
    [
     621,
     281
    ]
   ],
   "shape_type": "point",
   "flags": {}
  },
  {
   "label": "point",
   "line_color": null,
   "fill_color": null,
   "points": [
    [
     626,
     273
    ]
   ],
   "shape_type": "point",
   "flags": {}
  },
  {
   "label": "point",
   "line_color": null,
   "fill_color": null,
   "points": [
    [
     626,
     273
    ]
   ],
   "shape_type": "point",
   "flags": {}
  },
  {
   "label": "point",
   "line_color": null,
   "fill_color": null,
   "points": [
    [
     626,
     273
    ]
   ],
   "shape_type": "point",
   "flags": {}
  },
  {
   "label": "point",
   "line_color": null,
   "fill_color": null,
   "points": [
    [
     646,
     271
    ]
   ],
   "shape_type": "point",
   "flags": {}
  },
  {
   "label": "point",
   "line_color": null,
   "fill_color": null,
   "points": [
    [
     665,
     269
    ]
   ],
   "shape_type": "point",
   "flags": {}
  },
  {
   "label": "point",
   "line_color": null,
   "fill_color": null,
   "points": [
    [
     648,
     277
    ]
   ],
   "shape_type": "point",
   "flags": {}
  },
  {
   "label": "point",
   "line_color": null,
   "fill_color": null,
   "points": [
    [
     631,
     282
    ]
   ],
   "shape_type": "point",
   "flags": {}
  },
  {
   "label": "point",
   "line_color": null,
   "fill_color": null,
   "points": [
    [
     628,
     277
    ]
   ],
   "shape_type": "point",
   "flags": {}
  },
  {
   "label": "point",
   "line_color": null,
   "fill_color": null,
   "points": [
    [
     613,
     204
    ]
   ],
   "shape_type": "point",
   "flags": {}
  },
  {
   "label": "point",
   "line_color": null,
   "fill_color": null,
   "points": [
    [
     653,
     201
    ]
   ],
   "shape_type": "point",
   "flags": {}
  }
 ],
 "lineColor": [
  0,
  255,
  0,
  128
 ],
 "fillColor": [
  255,
  0,
  0,
  128
 ],
 "imagePath": "13_Interview_Interview_2_People_Visible_13_364.jpg",
 "imageData": null,
 "imageHeight": 1366,
 "imageWidth": 1024
}