{
 "version": "3.16.7",
 "flags": {},
 "shapes": [
  {
   "label": "box",
   "line_color": [
    0,
    255,
    0,
    255
   ],
   "fill_color": null,
   "points": [
    [
     140,
     96
    ],
    [
     306,
     312
    ]
   ],
   "shape_type": "rectangle",
   "flags": {}
  },
  {
   "label": "point",
   "line_color": null,
   "fill_color": null,
   "points": [
    [
     127,
     180
    ]
   ],
   "shape_type": "point",
   "flags": {}
  },
  {
   "label": "point",
   "line_color": null,
   "fill_color": null,
   "points": [
    [
     126,
     193
    ]
   ],
   "shape_type": "point",
   "flags": {}
  },
  {
   "label": "point",
   "line_color": null,
   "fill_color": null,
   "points": [
    [
     125,
     205
    ]
   ],
   "shape_type": "point",
   "flags": {}
  },
  {
   "label": "point",
   "line_color": null,
   "fill_color": null,
   "points": [
    [
     124,
     217
    ]
   ],
   "shape_type": "point",
   "flags": {}
  },
  {
   "label": "point",
   "line_color": null,
   "fill_color": null,
   "points": [
    [
     124,
     230
    ]
   ],
   "shape_type": "point",
   "flags": {}
  },
  {
   "label": "point",
   "line_color": null,
   "fill_color": null,
   "points": [
    [
     125,
     242
    ]
   ],
   "shape_type": "point",
   "flags": {}
  },
  {
   "label": "point",
   "line_color": null,
   "fill_color": null,
   "points": [
    [
     127,
     254
    ]
   ],
   "shape_type": "point",
   "flags": {}
  },
  {
   "label": "point",
   "line_color": null,
   "fill_color": null,
   "points": [
    [
     131,
     266
    ]
   ],
   "shape_type": "point",
   "flags": {}
  },
  {
   "label": "point",
   "line_color": null,
   "fill_color": null,
   "points": [
    [
     136,
     277
    ]
   ],
   "shape_type": "point",
   "flags": {}
  },
  {
   "label": "point",
   "line_color": null,
   "fill_color": null,
   "points": [
    [
     143,
     287
    ]
   ],
   "shape_type": "point",
   "flags": {}
  },
  {
   "label": "point",
   "line_color": null,
   "fill_color": null,
   "points": [
    [
     151,
     296
    ]
   ],
   "shape_type": "point",
   "flags": {}
  },
  {
   "label": "point",
   "line_color": null,
   "fill_color": null,
   "points": [
    [
     161,
     304
    ]
   ],
   "shape_type": "point",
   "flags": {}
  },
  {
   "label": "point",
   "line_color": null,
   "fill_color": null,
   "points": [
    [
     171,
     311
    ]
   ],
   "shape_type": "point",
   "flags": {}
  },
  {
   "label": "point",
   "line_color": null,
   "fill_color": null,
   "points": [
    [
     182,
     317
    ]
   ],
   "shape_type": "point",
   "flags": {}
  },
  {
   "label": "point",
   "line_color": null,
   "fill_color": null,
   "points": [
    [
     193,
     323
    ]
   ],
   "shape_type": "point",
   "flags": {}
  },
  {
   "label": "point",
   "line_color": null,
   "fill_color": null,
   "points": [
    [
     205,
     326
    ]
   ],
   "shape_type": "point",
   "flags": {}
  },
  {
   "label": "point",
   "line_color": null,
   "fill_color": null,
   "points": [
    [
     217,
     328
    ]
   ],
   "shape_type": "point",
   "flags": {}
  },
  {
   "label": "point",
   "line_color": null,
   "fill_color": null,
   "points": [
    [
     229,
     328
    ]
   ],
   "shape_type": "point",
   "flags": {}
  },
  {
   "label": "point",
   "line_color": null,
   "fill_color": null,
   "points": [
    [
     240,
     326
    ]
   ],
   "shape_type": "point",
   "flags": {}
  },
  {
   "label": "point",
   "line_color": null,
   "fill_color": null,
   "points": [
    [
     250,
     320
    ]
   ],
   "shape_type": "point",
   "flags": {}
  },
  {
   "label": "point",
   "line_color": null,
   "fill_color": null,
   "points": [
    [
     260,
     313
    ]
   ],
   "shape_type": "point",
   "flags": {}
  },
  {
   "label": "point",
   "line_color": null,
   "fill_color": null,
   "points": [
    [
     269,
     306
    ]
   ],
   "shape_type": "point",
   "flags": {}
  },
  {
   "label": "point",
   "line_color": null,
   "fill_color": null,
   "points": [
    [
     277,
     298
    ]
   ],
   "shape_type": "point",
   "flags": {}
  },
  {
   "label": "point",
   "line_color": null,
   "fill_color": null,
   "points": [
    [
     284,
     288
    ]
   ],
   "shape_type": "point",
   "flags": {}
  },
  {
   "label": "point",
   "line_color": null,
   "fill_color": null,
   "points": [
    [
     290,
     278
    ]
   ],
   "shape_type": "point",
   "flags": {}
  },
  {
   "label": "point",
   "line_color": null,
   "fill_color": null,
   "points": [
    [
     294,
     267
    ]
   ],
   "shape_type": "point",
   "flags": {}
  },
  {
   "label": "point",
   "line_color": null,
   "fill_color": null,
   "points": [
    [
     296,
     256
    ]
   ],
   "shape_type": "point",
   "flags": {}
  },
  {
   "label": "point",
   "line_color": null,
   "fill_color": null,
   "points": [
    [
     298,
     244
    ]
   ],
   "shape_type": "point",
   "flags": {}
  },
  {
   "label": "point",
   "line_color": null,
   "fill_color": null,
   "points": [
    [
     303,
     234
    ]
   ],
   "shape_type": "point",
   "flags": {}
  },
  {
   "label": "point",
   "line_color": null,
   "fill_color": null,
   "points": [
    [
     308,
     223
    ]
   ],
   "shape_type": "point",
   "flags": {}
  },
  {
   "label": "point",
   "line_color": null,
   "fill_color": null,
   "points": [
    [
     308,
     212
    ]
   ],
   "shape_type": "point",
   "flags": {}
  },
  {
   "label": "point",
   "line_color": null,
   "fill_color": null,
   "points": [
    [
     308,
     200
    ]
   ],
   "shape_type": "point",
   "flags": {}
  },
  {
   "label": "point",
   "line_color": null,
   "fill_color": null,
   "points": [
    [
     308,
     188
    ]
   ],
   "shape_type": "point",
   "flags": {}
  },
  {
   "label": "point",
   "line_color": null,
   "fill_color": null,
   "points": [
    [
     152,
     161
    ]
   ],
   "shape_type": "point",
   "flags": {}
  },
  {
   "label": "point",
   "line_color": null,
   "fill_color": null,
   "points": [
    [
     169,
     148
    ]
   ],
   "shape_type": "point",
   "flags": {}
  },
  {
   "label": "point",
   "line_color": null,
   "fill_color": null,
   "points": [
    [
     186,
     146
    ]
   ],
   "shape_type": "point",
   "flags": {}
  },
  {
   "label": "point",
   "line_color": null,
   "fill_color": null,
   "points": [
    [
     202,
     149
    ]
   ],
   "shape_type": "point",
   "flags": {}
  },
  {
   "label": "point",
   "line_color": null,
   "fill_color": null,
   "points": [
    [
     220,
     154
    ]
   ],
   "shape_type": "point",
   "flags": {}
  },
  {
   "label": "point",
   "line_color": null,
   "fill_color": null,
   "points": [
    [
     219,
     163
    ]
   ],
   "shape_type": "point",
   "flags": {}
  },
  {
   "label": "point",
   "line_color": null,
   "fill_color": null,
   "points": [
    [
     201,
     159
    ]
   ],
   "shape_type": "point",
   "flags": {}
  },
  {
   "label": "point",
   "line_color": null,
   "fill_color": null,
   "points": [
    [
     185,
     155
    ]
   ],
   "shape_type": "point",
   "flags": {}
  },
  {
   "label": "point",
   "line_color": null,
   "fill_color": null,
   "points": [
    [
     168,
     157
    ]
   ],
   "shape_type": "point",
   "flags": {}
  },
  {
   "label": "point",
   "line_color": null,
   "fill_color": null,
   "points": [
    [
     247,
     156
    ]
   ],
   "shape_type": "point",
   "flags": {}
  },
  {
   "label": "point",
   "line_color": null,
   "fill_color": null,
   "points": [
    [
     261,
     156
    ]
   ],
   "shape_type": "point",
   "flags": {}
  },
  {
   "label": "point",
   "line_color": null,
   "fill_color": null,
   "points": [
    [
     274,
     156
    ]
   ],
   "shape_type": "point",
   "flags": {}
  },
  {
   "label": "point",
   "line_color": null,
   "fill_color": null,
   "points": [
    [
     287,
     158
    ]
   ],
   "shape_type": "point",
   "flags": {}
  },
  {
   "label": "point",
   "line_color": null,
   "fill_color": null,
   "points": [
    [
     298,
     174
    ]
   ],
   "shape_type": "point",
   "flags": {}
  },
  {
   "label": "point",
   "line_color": null,
   "fill_color": null,
   "points": [
    [
     286,
     167
    ]
   ],
   "shape_type": "point",
   "flags": {}
  },
  {
   "label": "point",
   "line_color": null,
   "fill_color": null,
   "points": [
    [
     273,
     165
    ]
   ],
   "shape_type": "point",
   "flags": {}
  },
  {
   "label": "point",
   "line_color": null,
   "fill_color": null,
   "points": [
    [
     259,
     164
    ]
   ],
   "shape_type": "point",
   "flags": {}
  },
  {
   "label": "point",
   "line_color": null,
   "fill_color": null,
   "points": [
    [
     246,
     166
    ]
   ],
   "shape_type": "point",
   "flags": {}
  },
  {
   "label": "point",
   "line_color": null,
   "fill_color": null,
   "points": [
    [
     231,
     177
    ]
   ],
   "shape_type": "point",
   "flags": {}
  },
  {
   "label": "point",
   "line_color": null,
   "fill_color": null,
   "points": [
    [
     231,
     193
    ]
   ],
   "shape_type": "point",
   "flags": {}
  },
  {
   "label": "point",
   "line_color": null,
   "fill_color": null,
   "points": [
    [
     231,
     208
    ]
   ],
   "shape_type": "point",
   "flags": {}
  },
  {
   "label": "point",
   "line_color": null,
   "fill_color": null,
   "points": [
    [
     231,
     222
    ]
   ],
   "shape_type": "point",
   "flags": {}
  },
  {
   "label": "point",
   "line_color": null,
   "fill_color": null,
   "points": [
    [
     206,
     229
    ]
   ],
   "shape_type": "point",
   "flags": {}
  },
  {
   "label": "point",
   "line_color": null,
   "fill_color": null,
   "points": [
    [
     216,
     233
    ]
   ],
   "shape_type": "point",
   "flags": {}
  },
  {
   "label": "point",
   "line_color": null,
   "fill_color": null,
   "points": [
    [
     227,
     236
    ]
   ],
   "shape_type": "point",
   "flags": {}
  },
  {
   "label": "point",
   "line_color": null,
   "fill_color": null,
   "points": [
    [
     237,
     233
    ]
   ],
   "shape_type": "point",
   "flags": {}
  },
  {
   "label": "point",
   "line_color": null,
   "fill_color": null,
   "points": [
    [
     247,
     232
    ]
   ],
   "shape_type": "point",
   "flags": {}
  },
  {
   "label": "point",
   "line_color": null,
   "fill_color": null,
   "points": [
    [
     168,
     170
    ]
   ],
   "shape_type": "point",
   "flags": {}
  },
  {
   "label": "point",
   "line_color": null,
   "fill_color": null,
   "points": [
    [
     177,
     167
    ]
   ],
   "shape_type": "point",
   "flags": {}
  },
  {
   "label": "point",
   "line_color": null,
   "fill_color": null,
   "points": [
    [
     186,
     166
    ]
   ],
   "shape_type": "point",
   "flags": {}
  },
  {
   "label": "point",
   "line_color": null,
   "fill_color": null,
   "points": [
    [
     196,
     169
    ]
   ],
   "shape_type": "point",
   "flags": {}
  },
  {
   "label": "point",
   "line_color": null,
   "fill_color": null,
   "points": [
    [
     204,
     176
    ]
   ],
   "shape_type": "point",
   "flags": {}
  },
  {
   "label": "point",
   "line_color": null,
   "fill_color": null,
   "points": [
    [
     194,
     176
    ]
   ],
   "shape_type": "point",
   "flags": {}
  },
  {
   "label": "point",
   "line_color": null,
   "fill_color": null,
   "points": [
    [
     185,
     176
    ]
   ],
   "shape_type": "point",
   "flags": {}
  },
  {
   "label": "point",
   "line_color": null,
   "fill_color": null,
   "points": [
    [
     176,
     174
    ]
   ],
   "shape_type": "point",
   "flags": {}
  },
  {
   "label": "point",
   "line_color": null,
   "fill_color": null,
   "points": [
    [
     251,
     181
    ]
   ],
   "shape_type": "point",
   "flags": {}
  },
  {
   "label": "point",
   "line_color": null,
   "fill_color": null,
   "points": [
    [
     261,
     177
    ]
   ],
   "shape_type": "point",
   "flags": {}
  },
  {
   "label": "point",
   "line_color": null,
   "fill_color": null,
   "points": [
    [
     271,
     176
    ]
   ],
   "shape_type": "point",
   "flags": {}
  },
  {
   "label": "point",
   "line_color": null,
   "fill_color": null,
   "points": [
    [
     279,
     179
    ]
   ],
   "shape_type": "point",
   "flags": {}
  },
  {
   "label": "point",
   "line_color": null,
   "fill_color": null,
   "points": [
    [
     286,
     185
    ]
   ],
   "shape_type": "point",
   "flags": {}
  },
  {
   "label": "point",
   "line_color": null,
   "fill_color": null,
   "points": [
    [
     279,
     187
    ]
   ],
   "shape_type": "point",
   "flags": {}
  },
  {
   "label": "point",
   "line_color": null,
   "fill_color": null,
   "points": [
    [
     271,
     187
    ]
   ],
   "shape_type": "point",
   "flags": {}
  },
  {
   "label": "point",
   "line_color": null,
   "fill_color": null,
   "points": [
    [
     261,
     184
    ]
   ],
   "shape_type": "point",
   "flags": {}
  },
  {
   "label": "point",
   "line_color": null,
   "fill_color": null,
   "points": [
    [
     174,
     251
    ]
   ],
   "shape_type": "point",
   "flags": {}
  },
  {
   "label": "point",
   "line_color": null,
   "fill_color": null,
   "points": [
    [
     193,
     246
    ]
   ],
   "shape_type": "point",
   "flags": {}
  },
  {
   "label": "point",
   "line_color": null,
   "fill_color": null,
   "points": [
    [
     212,
     245
    ]
   ],
   "shape_type": "point",
   "flags": {}
  },
  {
   "label": "point",
   "line_color": null,
   "fill_color": null,
   "points": [
    [
     223,
     247
    ]
   ],
   "shape_type": "point",
   "flags": {}
  },
  {
   "label": "point",
   "line_color": null,
   "fill_color": null,
   "points": [
    [
     235,
     247
    ]
   ],
   "shape_type": "point",
   "flags": {}
  },
  {
   "label": "point",
   "line_color": null,
   "fill_color": null,
   "points": [
    [
     249,
     251
    ]
   ],
   "shape_type": "point",
   "flags": {}
  },
  {
   "label": "point",
   "line_color": null,
   "fill_color": null,
   "points": [
    [
     261,
     261
    ]
   ],
   "shape_type": "point",
   "flags": {}
  },
  {
   "label": "point",
   "line_color": null,
   "fill_color": null,
   "points": [
    [
     252,
     274
    ]
   ],
   "shape_type": "point",
   "flags": {}
  },
  {
   "label": "point",
   "line_color": null,
   "fill_color": null,
   "points": [
    [
     237,
     282
    ]
   ],
   "shape_type": "point",
   "flags": {}
  },
  {
   "label": "point",
   "line_color": null,
   "fill_color": null,
   "points": [
    [
     220,
     282
    ]
   ],
   "shape_type": "point",
   "flags": {}
  },
  {
   "label": "point",
   "line_color": null,
   "fill_color": null,
   "points": [
    [
     201,
     279
    ]
   ],
   "shape_type": "point",
   "flags": {}
  },
  {
   "label": "point",
   "line_color": null,
   "fill_color": null,
   "points": [
    [
     185,
     267
    ]
   ],
   "shape_type": "point",
   "flags": {}
  },
  {
   "label": "point",
   "line_color": null,
   "fill_color": null,
   "points": [
    [
     178,
     253
    ]
   ],
   "shape_type": "point",
   "flags": {}
  },
  {
   "label": "point",
   "line_color": null,
   "fill_color": null,
   "points": [
    [
     201,
     251
    ]
   ],
   "shape_type": "point",
   "flags": {}
  },
  {
   "label": "point",
   "line_color": null,
   "fill_color": null,
   "points": [
    [
     224,
     254
    ]
   ],
   "shape_type": "point",
   "flags": {}
  },
  {
   "label": "point",
   "line_color": null,
   "fill_color": null,
   "points": [
    [
     241,
     255
    ]
   ],
   "shape_type": "point",
   "flags": {}
  },
  {
   "label": "point",
   "line_color": null,
   "fill_color": null,
   "points": [
    [
     256,
     262
    ]
   ],
   "shape_type": "point",
   "flags": {}
  },
  {
   "label": "point",
   "line_color": null,
   "fill_color": null,
   "points": [
    [
     241,
     274
    ]
   ],
   "shape_type": "point",
   "flags": {}
  },
  {
   "label": "point",
   "line_color": null,
   "fill_color": null,
   "points": [
    [
     221,
     276
    ]
   ],
   "shape_type": "point",
   "flags": {}
  },
  {
   "label": "point",
   "line_color": null,
   "fill_color": null,
   "points": [
    [
     196,
     270
    ]
   ],
   "shape_type": "point",
   "flags": {}
  },
  {
   "label": "point",
   "line_color": null,
   "fill_color": null,
   "points": [
    [
     184,
     171
    ]
   ],
   "shape_type": "point",
   "flags": {}
  },
  {
   "label": "point",
   "line_color": null,
   "fill_color": null,
   "points": [
    [
     271,
     180
    ]
   ],
   "shape_type": "point",
   "flags": {}
  }
 ],
 "lineColor": [
  0,
  255,
  0,
  128
 ],
 "fillColor": [
  255,
  0,
  0,
  128
 ],
 "imagePath": "29_Students_Schoolkids_Students_Schoolkids_29_469.jpg",
 "imageData": null,
 "imageHeight": 683,
 "imageWidth": 1024
}